oidv6/OIDv6.py
oidv6/__init__.py
oidv6/modules/__init__.py
oidv6/modules/core/__init__.py
oidv6/modules/core/config.py
oidv6/modules/core/core.py
oidv6/modules/core/switch.py
oidv6/modules/locales/en/LC_MESSAGES/argparse.mo
oidv6/modules/locales/en/LC_MESSAGES/oidv6.mo
oidv6/modules/locales/ru/LC_MESSAGES/argparse.mo
oidv6/modules/locales/ru/LC_MESSAGES/oidv6.mo
oidv6/modules/trml/__init__.py
oidv6/modules/trml/shell.py
oidv6/samples/__init__.py
oidv6/samples/run.py
oidv6-1.0.5.dist-info/AUTHORS
oidv6-1.0.5.dist-info/LICENSE
oidv6-1.0.5.dist-info/METADATA
oidv6-1.0.5.dist-info/WHEEL
oidv6-1.0.5.dist-info/entry_points.txt
oidv6-1.0.5.dist-info/top_level.txt
oidv6-1.0.5.dist-info/RECORD
