Metadata-Version: 2.1
Name: oidv6
Version: 1.0.5
Summary: Download single or multiple classes from the Open Images V6 dataset
Home-page: https://github.com/DmitryRyumin/OIDv6
Author: Dmitry Ryumin
Author-email: dl_03.03.1991@mail.ru
Maintainer: Dmitry Ryumin
Maintainer-email: dl_03.03.1991@mail.ru
License: MIT
Keywords: oidv6,Open Images Dataset
Platform: UNKNOWN
Classifier: Development Status :: 5 - Production/Stable
Classifier: Natural Language :: Russian
Classifier: Natural Language :: English
Classifier: Intended Audience :: Developers
Classifier: Intended Audience :: Education
Classifier: Intended Audience :: Science/Research
Classifier: License :: OSI Approved :: MIT License
Classifier: Programming Language :: Python
Classifier: Programming Language :: Python :: 3
Classifier: Programming Language :: Python :: 3.7
Classifier: Programming Language :: Python :: 3.8
Classifier: Programming Language :: Python :: 3 :: Only
Classifier: Programming Language :: Python :: Implementation :: CPython
Classifier: Topic :: Scientific/Engineering
Classifier: Topic :: Scientific/Engineering :: Mathematics
Classifier: Topic :: Software Development
Classifier: Topic :: Software Development :: Libraries
Classifier: Topic :: Software Development :: Libraries :: Python Modules
Classifier: Operating System :: MacOS :: MacOS X
Classifier: Operating System :: Microsoft :: Windows
Classifier: Operating System :: POSIX :: Linux
Requires-Python: >=3.7
Requires-Dist: requests (>=2.23.0)
Requires-Dist: numpy (>=1.18.4)
Requires-Dist: pandas (>=1.0.4)
Requires-Dist: progressbar2 (>=3.51.3)
Requires-Dist: opencv-contrib-python (>=4.2.0.34)
Requires-Dist: awscli (>=1.18.69)
